MANIFEST.in
README.md
config.json
setup.py
deckster/__init__.py
deckster/main.py
deckster/common/configs.py
deckster/common/core.py
deckster/common/keys.py
deckster/common/scheduler.py
deckster/generators/generators.py
deckster/generators/builtins/steam.py
deckster/modules/api.py
deckster/plugins/builtins/exit.py
deckster/plugins/builtins/homeassistant.py
deckster/plugins/builtins/lock.py
deckster/plugins/builtins/play.py
deckster/plugins/builtins/shell.py
deckster/plugins/builtins/page/next.py
deckster/plugins/builtins/page/previous.py
deckster/plugins/builtins/web/get.py
deckster/plugins/builtins/web/post.py
deckster_sd.egg-info/PKG-INFO
deckster_sd.egg-info/SOURCES.txt
deckster_sd.egg-info/dependency_links.txt
deckster_sd.egg-info/entry_points.txt
deckster_sd.egg-info/requires.txt
deckster_sd.egg-info/top_level.txt
docs/changelog.md
docs/config.md
docs/custom_generators.md
docs/custom_plugins.md
docs/generators.md
docs/index.md
docs/install.md
docs/modules.md
docs/plugins.md