Metadata-Version: 2.1
Name: deckster-sd
Version: 0.6.2
Summary: A service to manage your Streamdeck easily on Linux
Home-page: https://github.com/Gabisonfire/Deckster
Author: Gabisonfire
Author-email: gabisonfire@github.com
License: UNKNOWN
Keywords: streamdeck
Platform: UNKNOWN
Classifier: Programming Language :: Python :: 3
Classifier: License :: OSI Approved :: GNU General Public License v3 (GPLv3)
Classifier: Operating System :: POSIX :: Linux
Classifier: Topic :: System :: Hardware
Requires-Python: >=3.9
